Metadata-Version: 2.1
Name: simple-password-manager
Version: 0.0.4
Summary: A simple password manager
Home-page: https://github.com/7alle9/Simple-Password-Manager
Author: Amir Mallek
Author-email: mallekamir123@gmail.com
Keywords: python,password,manager,simple,cli,security
Classifier: Development Status :: 4 - Beta
Classifier: Intended Audience :: Developers
Classifier: Intended Audience :: End Users/Desktop
Classifier: Topic :: Security :: Cryptography
Classifier: Topic :: Software Development :: Libraries :: Python Modules
Classifier: License :: OSI Approved :: MIT License
Classifier: Programming Language :: Python :: 3.8
Classifier: Programming Language :: Python :: 3.9
Classifier: Programming Language :: Python :: 3.10
Classifier: Operating System :: OS Independent
License-File: LICENSE
Requires-Dist: cryptography
Requires-Dist: requests
Requires-Dist: platformdirs
Requires-Dist: pyperclip
